LICENSE
MANIFEST.in
README.rst
requirements.txt
sanic_sentry.py
setup.py
sanic_sentry.egg-info/PKG-INFO
sanic_sentry.egg-info/SOURCES.txt
sanic_sentry.egg-info/dependency_links.txt
sanic_sentry.egg-info/requires.txt
sanic_sentry.egg-info/top_level.txt