Metadata-Version: 1.1
Name: sanic-sentry
Version: 0.1.6
Summary: Sentry integration to sanic web server
Home-page: https://github.com/serathius/sanic-sentry
Author: Marek Siarkowicz
Author-email: UNKNOWN
License: MIT
Keywords: sanic,sentry
Platform: Any
Classifier: Development Status :: 3 - Alpha
Classifier: Intended Audience :: Developers
Classifier: License :: OSI Approved :: MIT License
Classifier: Natural Language :: English
Classifier: Operating System :: OS Independent
Classifier: Programming Language :: Python
Classifier: Programming Language :: Python :: 3.5
Classifier: Programming Language :: Python :: 3.6
Classifier: Programming Language :: Python :: 3 :: Only
Classifier: Topic :: Software Development :: Libraries :: Python Modules
Classifier: Topic :: Software Development :: Testing
Classifier: Topic :: Utilities
